{"updates":[
{
"term": "노인 구강건조증",
"detail": "<p><strong>노인 구강건조증(Xerostomia in Elderly)</strong>은 65세 이상에서 흔히 발생하는 침 분비 감소 상태입니다. 단순 불편을 넘어 충치·잇몸병·연하장애·삶의 질 저하로 직결되는 노인 구강건강의 핵심 문제입니다.</p><h3>유병률과 원인</h3><p>65세 이상의 약 30%, 75세 이상은 40-50%가 호소합니다. 노화 자체보다는 <strong>약물 부작용</strong>이 가장 큰 원인입니다.</p><h3>주요 원인 약물</h3><table><thead><tr><th>약물 분류</th><th>예시</th></tr></thead><tbody><tr><td>항고혈압제</td><td>이뇨제, 베타차단제</td></tr><tr><td>항우울제</td><td>SSRI, 삼환계</td></tr><tr><td>항히스타민제</td><td>알레르기·감기약</td></tr><tr><td>이뇨제</td><td>푸로세미드 등</td></tr><tr><td>항파킨슨 약물</td><td>레보도파</td></tr><tr><td>항암 치료</td><td>방사선, 항암제</td></tr></tbody></table><p>5가지 이상 약물 복용(다약제 복용) 노인은 80% 이상이 구강건조증을 겪습니다.</p><h3>구강 합병증</h3><ul><li><strong>급속한 다발성 우식</strong>: 특히 <a href='/encyclopedia/%EB%85%B8%EC%9D%B8%20%EB%BF%8C%EB%A6%AC%20%EC%9A%B0%EC%8B%9D'>뿌리 우식</a> 급증</li><li><strong>구강 칸디다증</strong>: 침의 항균 작용 감소</li><li><strong>의치 적응 곤란</strong>: 침이 마찰 줄여줘야 의치 안정</li><li><strong>연하·발음 장애</strong>: 음식 삼키기 어려움</li><li><strong>미각 변화</strong>: 맛을 잘 못 느낌</li></ul><h3>관리 전략</h3><ol><li><strong>약물 조정</strong>: 주치의와 상의해 대체 약 가능 시 변경</li><li><strong>수분 섭취</strong>: 하루 1.5-2L, 자주 조금씩</li><li><strong>인공 침</strong>: 글리세린 기반 제품, 자기 전 사용</li><li><strong>침 자극제</strong>: 무설탕 껌, 자일리톨 사탕</li><li><strong>불소 강화</strong>: 고농도 불소 치약(5000ppm), 정기 <a href='/encyclopedia/%EB%B6%88%EC%86%8C%20%EB%8F%84%ED%8F%AC'>불소 도포</a></li><li><strong>야간 가습기</strong>: 입 벌리고 자는 노인에 필수</li></ol><h3>피해야 할 것</h3><ul><li>카페인, 알코올 (이뇨 작용)</li><li>알코올 함유 구강세정제 (자극)</li><li>건조한 빵·과자 (삼키기 어려움)</li><li>흡연 (침샘 위축)</li></ul>",
"link": null,
"guide": null
},
{
"term": "노인 뿌리 우식",
"detail": "<p><strong>노인 뿌리 우식(Root Caries)</strong>은 잇몸이 내려가면서 노출된 치아 뿌리 표면에 생기는 충치입니다. 65세 이상의 30-50%에서 발견되며, 노인 치아 상실의 주요 원인입니다.</p><h3>왜 노인에게 흔한가</h3><ul><li><strong>잇몸 퇴축</strong>: 나이 들수록 잇몸이 내려가 뿌리(상아질) 노출</li><li><strong><a href='/encyclopedia/%EB%85%B8%EC%9D%B8%20%EA%B5%AC%EA%B0%95%EA%B1%B4%EC%A1%B0%EC%A6%9D'>구강건조증</a></strong>: 침이 충치 진행을 막아주는데 줄어듦</li><li><strong>치아 위생 곤란</strong>: 손 떨림, 시력 저하로 칫솔질 어려움</li><li><strong>상아질의 약함</strong>: 법랑질보다 빨리 진행</li></ul><h3>법랑질 vs 상아질 우식 차이</h3><table><thead><tr><th>구분</th><th>법랑질 우식</th><th>뿌리 우식(상아질)</th></tr></thead><tbody><tr><td>위치</td><td>치아 머리</td><td>치아 뿌리, 치경부</td></tr><tr><td>진행 속도</td><td>느림</td><td>빠름 (3-5배)</td></tr><tr><td>임계 pH</td><td>5.5</td><td>6.2 (더 잘 녹음)</td></tr><tr><td>색</td><td>흰점 → 갈색</td><td>노란/갈색, 부드러움</td></tr><tr><td>통증</td><td>늦게 발생</td><td>일찍 시린감</td></tr></tbody></table><h3>특히 위험한 부위</h3><ul><li><strong>치아 사이</strong>: 칫솔이 안 닿는 영역</li><li><strong>최후방 어금니</strong>: 시야·접근 어려움</li><li><strong>틀니 걸쇠 닿는 치아</strong>: 플라크 축적</li></ul><h3>예방 전략</h3><ol><li><strong>고농도 불소 치약</strong>: 5000ppm 처방용, 일반 치약의 3배</li><li><strong>정기 불소 도포</strong>: 3개월마다 치과에서</li><li><strong>치간칫솔</strong>: 치실보다 효과적 (노인 손에 더 쉬움)</li><li><strong>전동 칫솔</strong>: 손 떨림 보완</li><li><strong>식이 조절</strong>: 잦은 단 음식·음료 자제</li><li><strong>3-4개월 검진</strong>: 일반인 6개월보다 짧게</li></ol><h3>치료 시 고려사항</h3><p>뿌리 우식은 잇몸 라인에 걸려 격리(방습)가 어렵고, 충치 깊이 가늠이 어렵습니다. 글래스 아이오노머(GIC)를 우선 사용하는 경우가 많은데, 불소를 지속 방출해 재발을 막기 때문입니다.</p>",
"link": null,
"guide": null
},
{
"term": "노인 의치 적응",
"detail": "<p><strong>노인 의치 적응</strong>은 새로운 틀니에 익숙해지는 과정입니다. 평균 2-6주, 길게는 3-6개월까지 필요할 수 있습니다. 70세 이상 노인은 인지·근육 기능 변화로 젊은 환자보다 적응이 어렵습니다.</p><h3>적응 단계별 증상</h3><table><thead><tr><th>기간</th><th>흔한 증상</th><th>대처</th></tr></thead><tbody><tr><td>1주</td><td>입안 가득 찬 느낌, 침 많이 남, 발음 어색</td><td>물·죽 위주, 천천히 적응</td></tr><tr><td>2-3주</td><td>특정 부위 통증, 잇몸 압통</td><td>조정 1-2회 필요</td></tr><tr><td>1개월</td><td>씹기 가능, 발음 회복</td><td>식단 단계적 확장</td></tr><tr><td>3개월</td><td>완전 적응</td><td>정기 점검</td></tr></tbody></table><h3>의치 적응을 방해하는 요인</h3><ul><li><strong>구강건조증</strong>: 침이 의치 흡착을 도움, 마르면 쉽게 떨어짐</li><li><strong>치매·인지장애</strong>: 의치 끼고 빼기 자체를 잊음</li><li><strong>근력 약화</strong>: 혀·볼 근육이 의치를 못 잡아줌</li><li><strong>잇몸 위축</strong>: 시간 지나면 의치가 헐거워짐</li></ul><h3>가족 도움이 필수</h3><ol><li><strong>의치 끼고 빼기 도움</strong>: 손 떨리는 노인에게 위험</li><li><strong>매일 청소 확인</strong>: 자기 전 빼서 의치 세정제에 보관</li><li><strong>의치 분실 방지</strong>: 같은 곳에 두는 습관</li><li><strong>식사 시 함께</strong>: 사레, 입 베임 주의</li></ol><h3>적응 도와주는 식단 진행</h3><ul><li><strong>1주차</strong>: 죽, 미음, 으깬 음식, 요거트</li><li><strong>2주차</strong>: 부드러운 밥, 두부, 익은 나물</li><li><strong>3-4주차</strong>: 일반 밥, 잘게 썬 고기·채소</li><li><strong>주의</strong>: 평생 견과류·딱딱한 음식은 제한</li></ul><h3>적응 안 될 때 신호</h3><p>한 달 넘게 통증 지속, 자꾸 빠짐, 발음 회복 안 됨, 체중 감소 → 의치 재제작 또는 <a href='/encyclopedia/%EC%9E%84%ED%94%8C%EB%9E%80%ED%8A%B8%20%EC%98%A4%EB%B2%84%EB%8D%B4%EC%B3%98'>임플란트 오버덴쳐</a> 고려.</p>",
"link": "/treatments/dentures",
"guide": null
},
{
"term": "노인 연하장애",
"detail": "<p><strong>노인 연하장애(Dysphagia)</strong>는 음식을 입에서 위로 보내는 능력이 떨어진 상태입니다. 65세 이상 약 15%, 요양시설 입소자는 40-60%에서 발생하며, 흡인성 폐렴의 주요 원인입니다.</p><h3>치과와 연하장애</h3><p>씹기(저작)는 삼킴의 첫 단계입니다. 치아가 없거나 의치가 부적합하면 음식을 충분히 잘게 만들지 못해 연하장애가 악화됩니다. 한국 연구에 따르면 <strong>치아 20개 이하 노인은 연하장애 위험이 2.5배 높습니다.</strong></p><h3>주요 증상</h3><ul><li>식사 중 사레 잦음 (특히 물)</li><li>음식이 목에 걸린 느낌</li><li>식후 가래·기침 증가</li><li>체중 감소, 영양 부족</li><li>반복적인 폐렴</li></ul><h3>치과적 평가</h3><table><thead><tr><th>항목</th><th>확인 사항</th></tr></thead><tbody><tr><td>저작 능력</td><td>씹는 효율, 좌우 균형</td></tr><tr><td>치아 수</td><td>20개 미만이면 위험</td></tr><tr><td>의치 적합도</td><td>흔들림, 통증 부위</td></tr><tr><td><a href='/encyclopedia/%EB%85%B8%EC%9D%B8%20%EA%B5%AC%EA%B0%95%EA%B1%B4%EC%A1%B0%EC%A6%9D'>구강건조</a></td><td>침 분비, 음식 덩어리 형성</td></tr><tr><td>혀 근력</td><td>음식 후방 이동 능력</td></tr></tbody></table><h3>흡인성 폐렴 예방</h3><p>구강 내 세균이 침과 함께 폐로 흡인되면 폐렴 발생. 치주병 세균이 폐렴 원인균과 일치한다는 연구가 다수입니다. 따라서:</p><ol><li><strong>구강 위생</strong>: 가족·요양 인력이 도와서라도 매일 닦기</li><li><strong>치주 관리</strong>: 3개월 정기 스케일링</li><li><strong>의치 청소</strong>: 매일 의치 빼고 닦기</li><li><strong>식사 자세</strong>: 똑바로 앉아서 식사</li><li><strong>식이 점도</strong>: 너무 묽은 액체는 위험, 점도증진제 활용</li></ol><h3>다학제 협력</h3><p>치과(저작)·재활의학과(연하재활)·이비인후과(검사)·영양사(점도 조절) 협진이 이상적입니다. 큰 병원의 '연하 클리닉'이 있다면 우선 검사 권장.</p>",
"link": null,
"guide": null
},
{
"term": "노인 치과 진정",
"detail": "<p><strong>노인 치과 진정(Sedation in Geriatric Dentistry)</strong>은 고령 환자가 치과 치료에 협조하기 어려울 때 사용하는 진정요법입니다. 단, 노인은 약물 대사 능력이 떨어져 일반 성인과 다른 접근이 필요합니다.</p><h3>노인 진정이 필요한 경우</h3><ul><li><strong>치매·인지장애</strong>: 치료 협조 불가</li><li><strong>심한 치과 공포</strong>: 평생 누적된 공포</li><li><strong>파킨슨병</strong>: 떨림으로 정밀 시술 어려움</li><li><strong>장시간 시술</strong>: 임플란트 다수 식립</li><li><strong>구역 반사 심함</strong>: 인상·치료 자체 어려움</li></ul><h3>노인 진정의 특수성</h3><table><thead><tr><th>요인</th><th>일반 성인과의 차이</th></tr></thead><tbody><tr><td>약물 대사</td><td>간·신장 기능 저하, 효과 길어짐</td></tr><tr><td>약물 농도</td><td>지방·근육 비율 변화, 농도 예측 어려움</td></tr><tr><td>다약제 복용</td><td>상호작용 위험 ↑</td></tr><tr><td>심혈관 예비력</td><td>혈압·맥박 변동 견디기 어려움</td></tr><tr><td>회복 시간</td><td>1.5-2배 길어짐</td></tr></tbody></table><h3>안전한 진정 방법</h3><ol><li><strong>아산화질소(웃음가스)</strong>: 가장 안전, 즉시 회복, 노인에 1순위</li><li><strong>경구 진정</strong>: 트리아졸람 등 저용량, 일반 성인의 1/2-1/3</li><li><strong>정맥 진정</strong>: 미다졸람, 마취과 협진 필수</li><li><strong>전신마취</strong>: 위험 ↑, 종합병원 권장</li></ol><h3>사전 평가 필수 항목</h3><ul><li><strong>ASA 등급</strong>: 3-4등급은 종합병원 권장</li><li><strong>심전도(ECG)</strong>: 부정맥, 심방세동 확인</li><li><strong>복용 약물 전체</strong>: 와파린, 항혈소판제, 정신과 약</li><li><strong>최근 입원·수술</strong>: 1개월 이내면 신중</li><li><strong>보호자 동반</strong>: 진정 후 단독 귀가 절대 불가</li></ul><h3>진정 후 회복</h3><p>최소 1-2시간 회복실 모니터링. 보호자가 24시간 곁에 있어야 하며, 당일 운전·조리·중요 결정 금지. 일반 성인보다 2배 주의.</p>",
"link": null,
"guide": null
},
{
"term": "비급여 동의서",
"detail": "<p><strong>비급여 동의서</strong>는 건강보험 적용이 안 되는 치료(비급여)를 환자가 충분히 이해하고 동의했음을 서면으로 확인하는 문서입니다. 의료법상 의무 사항으로, 미작성 시 치과가 행정 처분을 받을 수 있습니다.</p><h3>법적 근거</h3><p>의료법 제45조 및 동법 시행규칙 제42조의 2에 따라, 비급여 진료비를 받기 위해서는 환자에게 사전 설명하고 서면 동의를 받아야 합니다.</p><h3>동의서 필수 기재 사항</h3><ul><li><strong>비급여 항목명</strong>: 예) 임플란트, 라미네이트, 미백</li><li><strong>비급여 사유</strong>: 미용 목적, 보험 미적용 재료 등</li><li><strong>예상 비용</strong>: 정확한 금액 또는 범위</li><li><strong>대체 가능 치료</strong>: 보험 적용 대안 (있는 경우)</li><li><strong>합병증·부작용</strong>: 가능한 위험</li><li><strong>환자 서명·날짜</strong></li><li><strong>설명한 의사 성명</strong></li></ul><h3>대표적 비급여 항목</h3><table><thead><tr><th>분야</th><th>예시</th></tr></thead><tbody><tr><td>임플란트</td><td>대부분 (단 65세 이상 2개 보험)</td></tr><tr><td>심미 치료</td><td>라미네이트, 미백, 심미 보철</td></tr><tr><td>교정</td><td>대부분 (구순구개열 제외)</td></tr><tr><td>틀니</td><td>일부 (탄성, 정밀)</td></tr><tr><td>보철</td><td>지르코니아, 금</td></tr></tbody></table><h3>환자의 권리</h3><ol><li><strong>충분한 설명 받을 권리</strong>: 이해될 때까지 질문</li><li><strong>견적서 요청</strong>: 시행 전 서면 견적 요구 가능</li><li><strong>대안 안내 받을 권리</strong>: 보험 적용 치료 옵션</li><li><strong>거절할 권리</strong>: 동의서 서명은 의무 아님</li><li><strong>사본 보관</strong>: 동의서 1부 반드시 받기</li></ol><h3>분쟁 예방 팁</h3><ul><li>금액 변동 시 추가 동의서 받기</li><li>구두 약속은 반드시 서면화</li><li>녹음·녹화는 사전 동의 필요</li><li>설명일과 시술일이 다르면 양일 모두 서명</li></ul><h3>병원이 안 받으면?</h3><p>비급여 동의서 없이 치료받았다면 보건소 또는 건강보험심사평가원에 민원 제기 가능. 부당 청구 시 환불 받을 수 있습니다.</p>",
"link": null,
"guide": "/guide/dental-cost"
},
{
"term": "의료비 세액공제",
"detail": "<p><strong>의료비 세액공제</strong>는 연간 지출한 의료비의 일부를 소득세에서 공제받는 제도입니다. 치과 치료비 대부분이 포함되어, 고액 치료 시 상당한 세금 절감 효과가 있습니다.</p><h3>공제 방식</h3><p>본인·부양가족 의료비 중 <strong>총급여의 3% 초과분</strong>에 대해 15%(난임 30%, 미숙아 20%)를 산출세액에서 공제. 한도는 본인·65세 이상·장애인 등은 무제한, 그 외 부양가족은 연 700만원.</p><h3>공제 대상 치과 비용</h3><table><thead><tr><th>구분</th><th>공제 가능</th><th>공제 불가</th></tr></thead><tbody><tr><td>치료 목적</td><td>충치, 치주, 임플란트, 보철, 신경치료</td><td>-</td></tr><tr><td>예방</td><td>스케일링, 치과 검진</td><td>-</td></tr><tr><td>교정</td><td>저작 기능 개선용 (의사 소견)</td><td>심미 목적</td></tr><tr><td>미용</td><td>-</td><td>미백, 라미네이트(미용)</td></tr><tr><td>보철</td><td>틀니, 일반 보철</td><td>-</td></tr></tbody></table><h3>공제 받는 방법</h3><ol><li><strong>국세청 홈택스</strong>: '연말정산 미리보기'에서 자동 조회</li><li><strong>현금 영수증·신용카드</strong>: 자동 집계</li><li><strong>현금 결제</strong>: 영수증 직접 보관, 별도 신고</li><li><strong>해외 치료</strong>: 영수증 환산 후 별도 신고</li><li><strong>의료비 명세서</strong>: 치과에 요청 가능 (연 1회)</li></ol><h3>실비보험 받은 금액은?</h3><p>실손보험에서 보상받은 금액은 본인 부담이 아니므로 <strong>공제 대상에서 제외</strong>됩니다. 본인이 실제 부담한 금액만 공제 신청 가능.</p><h3>치과 비용 공제 팁</h3><ul><li><strong>치료 시점 분산</strong>: 1년에 몰리면 한도 초과로 손해</li><li><strong>가족 의료비 통합</strong>: 소득 높은 사람 명의로 몰면 효과 ↑</li><li><strong>65세 이상 부모</strong>: 한도 무제한, 부양가족 등록 후 신청</li><li><strong>임플란트</strong>: 보험 임플란트는 본인부담금만, 비급여는 전액 공제</li><li><strong>교정 진단서</strong>: 저작 개선 목적임을 명시</li></ul><h3>예시 계산</h3><p>총급여 5000만원, 치과비 600만원 지출 시: 5000×3%=150만원 초과분 = 450만원 × 15% = <strong>약 67만원 세금 절감</strong>.</p>",
"link": null,
"guide": "/guide/dental-cost"
},
{
"term": "실비보험 청구",
"detail": "<p><strong>실비보험 청구(실손의료비)</strong>는 가입한 실손보험으로 치과 치료비를 환급받는 절차입니다. 모든 치과 치료가 대상은 아니며, 약관과 가입 시점에 따라 보장 범위가 크게 다릅니다.</p><h3>실비보험 치과 보장 원칙</h3><p>실손보험은 원칙적으로 <strong>건강보험 급여 항목</strong>만 보장합니다. 비급여 치과는 대부분 보장 제외이며, 다음과 같은 예외가 있습니다.</p><h3>보장 가능 vs 불가</h3><table><thead><tr><th>분야</th><th>보장</th><th>이유</th></tr></thead><tbody><tr><td>충치·신경치료</td><td>✅ 보장</td><td>급여 항목</td></tr><tr><td>치주 치료, 스케일링</td><td>✅ 보장 (조건부)</td><td>의사 처방 시</td></tr><tr><td>발치</td><td>✅ 보장</td><td>급여 항목</td></tr><tr><td>충치 레진</td><td>일부 ✅</td><td>2019년 이후 12세 이하 급여</td></tr><tr><td>임플란트</td><td>대부분 ❌</td><td>비급여 (65세 보험 임플란트 제외)</td></tr><tr><td>교정</td><td>❌</td><td>대부분 비급여</td></tr><tr><td>틀니</td><td>일부 ✅</td><td>65세 이상 보험 틀니</td></tr><tr><td>미백·라미네이트</td><td>❌</td><td>미용 목적</td></tr></tbody></table><h3>청구 시 필요 서류</h3><ol><li><strong>진료비 영수증</strong>: 원본</li><li><strong>진료비 세부내역서</strong>: 급여·비급여 구분 명시</li><li><strong>진단서/진료확인서</strong>: 30만원 초과 시 권장</li><li><strong>처방전·약 영수증</strong>: 약 처방 시</li><li><strong>본인 통장 사본</strong>: 첫 청구 시</li></ol><h3>청구 절차</h3><ol><li><strong>치과에서 서류 발급</strong>: 영수증·내역서 (수수료 1000-3000원)</li><li><strong>보험사 앱·홈페이지</strong>: 사진 첨부 청구 (50만원 이하)</li><li><strong>50만원 초과</strong>: 우편 또는 지점 방문, 원본 제출</li><li><strong>심사 (3-7영업일)</strong>: 보험사 검토</li><li><strong>입금</strong>: 본인 계좌로</li></ol><h3>청구 시 주의사항</h3><ul><li><strong>3년 시효</strong>: 진료일로부터 3년 내 청구</li><li><strong>자기부담금</strong>: 보통 외래 1만원, 입원 10%</li><li><strong>한도 확인</strong>: 1일 한도, 연간 한도</li><li><strong>여러 영수증 일괄</strong>: 가능, 자기부담금 1회만 적용</li><li><strong>가입 시점</strong>: 1세대(2009년 이전)는 보장 넓음</li></ul><h3>거절 시 대처</h3><p>1차 거절되어도 약관·진단서로 이의 제기 가능. 금융감독원 분쟁조정도 활용.</p>",
"link": null,
"guide": "/guide/dental-cost"
},
{
"term": "치과 산정특례",
"detail": "<p><strong>치과 산정특례</strong>는 특정 중증질환에 대해 건강보험 본인부담률을 5-10%로 낮춰주는 제도입니다. 치과 영역에서는 구강암, 구순구개열 등 일부에 적용됩니다.</p><h3>치과 적용 대상 질환</h3><table><thead><tr><th>질환</th><th>본인부담률</th><th>적용 기간</th></tr></thead><tbody><tr><td>구강암(악성 종양)</td><td>5%</td><td>5년</td></tr><tr><td>구순구개열</td><td>0% (만 6세 미만)</td><td>해당 연령까지</td></tr><tr><td>희귀난치질환</td><td>10%</td><td>5년</td></tr><tr><td>중증화상</td><td>5%</td><td>1-2년</td></tr><tr><td>턱뼈 골절(중증외상)</td><td>5%</td><td>30일</td></tr></tbody></table><h3>적용 받는 방법</h3><ol><li><strong>진단</strong>: 종합병원·대학병원에서 확진</li><li><strong>등록 신청</strong>: 의사가 산정특례 등록 신청서 작성</li><li><strong>건강보험공단</strong>: 자동 등록 통보</li><li><strong>치료 시</strong>: 자동 적용, 별도 신청 불필요</li></ol><h3>구강암 산정특례 상세</h3><p>혀암, 입바닥암, 잇몸암, 입천장암, 침샘암 등 구강 내 악성 종양 모두 포함. 치료 관련 치과 치료(예: 방사선 치료 전 발치)도 적용 가능.</p><h3>주의: 일반 치과 치료는 미적용</h3><ul><li>임플란트, 보철, 교정 등 일반 비급여는 산정특례와 무관</li><li>충치, 치주 등 보험 치과는 일반 본인부담률(30%) 적용</li><li>단, 등록 환자의 등록 질환 관련 치료는 5%</li></ul><h3>구순구개열 특례</h3><p>만 6세 미만은 본인부담 0%. 수술, 교정, 보철, 언어치료 등 광범위 적용. 만 6세 이후에는 일반 보험 적용되나 일부 의료기관에서 자체 감면 운영.</p><h3>중복 적용 시</h3><p>실비보험과 산정특례는 중복 적용 가능. 산정특례로 본인부담금이 줄고, 그 줄어든 금액에 대해 실비보험 청구 가능.</p>",
"link": null,
"guide": "/guide/dental-cost"
},
{
"term": "치과 본인부담금",
"detail": "<p><strong>치과 본인부담금</strong>은 건강보험 적용 치과 치료에서 환자가 직접 내는 금액입니다. 보험 적용분의 30%(외래 기준)가 기본이며, 연령·기관·치료 유형에 따라 달라집니다.</p><h3>외래 본인부담률</h3><table><thead><tr><th>기관</th><th>본인부담률</th></tr></thead><tbody><tr><td>의원급(개인 치과)</td><td>30%</td></tr><tr><td>병원급</td><td>40%</td></tr><tr><td>종합병원</td><td>50%</td></tr><tr><td>상급종합병원</td><td>60%</td></tr></tbody></table><p>치과는 대부분 의원급이라 30% 적용. 동네 치과가 가장 저렴한 이유.</p><h3>연령별 특례</h3><ul><li><strong>6세 미만</strong>: 외래 21% (의원), 입원 10%</li><li><strong>65세 이상</strong>: 진료비 1만 5천원 이하 1500원 정액, 초과 시 일반 적용</li><li><strong>치과 임플란트(보험)</strong>: 65세 이상 30% (일반), 차상위 20%, 의료급여 10-30%</li><li><strong>치과 틀니(보험)</strong>: 65세 이상 30% (일반)</li></ul><h3>주요 치료 본인부담금 예시 (2024년 기준)</h3><table><thead><tr><th>치료</th><th>총 수가</th><th>본인부담(30%)</th></tr></thead><tbody><tr><td>치주 치료(1/3악)</td><td>약 20,000원</td><td>약 6,000원</td></tr><tr><td>스케일링(연 1회)</td><td>약 38,000원</td><td>약 11,000원</td></tr><tr><td>충치 1면(아말감)</td><td>약 18,000원</td><td>약 5,400원</td></tr><tr><td>신경치료(전치, 3회)</td><td>약 80,000원</td><td>약 24,000원</td></tr><tr><td>발치(단순)</td><td>약 15,000원</td><td>약 4,500원</td></tr><tr><td>보험 임플란트(1개)</td><td>약 1,200,000원</td><td>약 360,000원</td></tr></tbody></table><p>※ 정확한 금액은 치료 난이도, 사용 재료에 따라 달라짐.</p><h3>본인부담금 면제·경감</h3><ul><li><strong>차상위 본인부담경감</strong>: 14%</li><li><strong>의료급여 1종</strong>: 외래 1000-1500원</li><li><strong>의료급여 2종</strong>: 외래 15%</li><li><strong>중증질환 산정특례</strong>: 5-10%</li><li><strong>희귀질환</strong>: 10%</li></ul><h3>본인부담상한제</h3><p>연간 본인부담금이 소득분위별 상한액(약 87만-808만원)을 초과하면 초과액을 건강보험공단에서 환급. 단, 비급여·선택진료비는 제외.</p><h3>치과는 비급여 비중이 크다</h3><p>치과의 60-70%가 비급여라 실제 환자 부담은 본인부담금보다 큽니다. <a href='/encyclopedia/%EB%B9%84%EA%B8%89%EC%97%AC%20%EB%8F%99%EC%9D%98%EC%84%9C'>비급여 동의서</a>를 통해 사전 견적 확인 필수.</p>",
"link": null,
"guide": "/guide/dental-cost"
}
]}
